{
    "colors": {
      "brand": {
        "primary": {
          "10": { "hex": "#054DFC", "id": "L90" },
          "20": { "hex": "#C2D4FF", "id": "L80" },
          "30": { "hex": "#1D45A8", "id": "L70" }
        },
        "secondary": {
          "10": { "hex": "#FFFFFF", "id": "L90" }
        },
        "base": {
          "10": { "hex": "#1A1A1A", "id": "L90" }
        }
      },
      "support": {
        "information": {
          "10": { "hex": "#E0E0E0", "id": "L90" }
        },
        "error": {
          "10": { "hex": "#F03D3D", "id": "L90" }
        },
        "warning": {
          "10": { "hex": "#FFCE52", "id": "L90" }
        },
        "success": {
          "10": { "hex": "#0BB07B", "id": "L90" }
        },
        "message": {
          "10": { "hex": "#2962FF", "id": "L90" }
        }
      }
    },
    "typography": {
      "weight": {
        "light": 300,
        "regular": 400,
        "bold": 700,
        "black": 900
      },
      "text": {
        "xlarge": {
          "fontSize": "28px",
          "lineHeight": "32px",
          "fontWeight": "700" 
        },
        "large": {
          "fontSize": "24px",
          "lineHeight": "28px",
          "fontWeight": "700" 
        },
        "medium": {
          "fontSize": "18px",
          "lineHeight": "24px",
          "fontWeight": "400" 
        },
        "small": {
          "fontSize": "16px",
          "lineHeight": "20px",
          "fontWeight": "400" 
        },
        "xsmall": {
          "fontSize": "14px",
          "lineHeight": "18px",
          "fontWeight": "300" 
        }
      }
    },
    "border": {
      "small": "10px",
      "medium": "20px",
      "pill": "1000px"
    }
  }
  